flask_sqlalchemy_crud/__init__.py
flask_sqlalchemy_crud/core.py
flask_sqlalchemy_crud/crud.py
flask_sqlalchemy_crud/query.py
flask_sqlalchemy_crud/status.py
flask_sqlalchemy_crud/transaction.py
flask_sqlalchemy_crud/types.py
flask_sqlalchemy_crud-0.1.0.dist-info/licenses/LICENSE
flask_sqlalchemy_crud-0.1.0.dist-info/METADATA
flask_sqlalchemy_crud-0.1.0.dist-info/WHEEL
flask_sqlalchemy_crud-0.1.0.dist-info/top_level.txt
flask_sqlalchemy_crud-0.1.0.dist-info/RECORD
