Metadata-Version: 2.4
Name: flask-sqlalchemy-crud
Version: 0.1.0
Summary: Use SQLAlchemy in a Pythonic way.
Author: ZMKimu
License: MIT
Project-URL: Homepage, https://github.com/ZM-Kimu/flask_sqlalchemy_crud
Requires-Python: >=3.11
License-File: LICENSE
Requires-Dist: flask-sqlalchemy>=3.0
Requires-Dist: sqlalchemy>=1.4
Dynamic: license-file
